my_fetchers/__init__.py
my_fetchers/get_all_links.py
my_fetchers-0.1.0.dist-info/WHEEL
my_fetchers-0.1.0.dist-info/METADATA
my_fetchers-0.1.0.dist-info/RECORD
