Metadata-Version: 2.1
Name: my-fetchers
Version: 0.1.0
Summary: Web Scrapper
Author: ehsan.tavan
Author-email: ehsan.tavan@gmail.com
Requires-Python: >=3.8,<4.0
Classifier: Programming Language :: Python :: 3
Classifier: Programming Language :: Python :: 3.10
Classifier: Programming Language :: Python :: 3.8
Classifier: Programming Language :: Python :: 3.9
Requires-Dist: beautifulsoup4 (==4.10.0)
Requires-Dist: requests (==2.26.0)
